datarobot_drum/__init__.py
datarobot_drum/custom_task_interfaces/__init__.py
datarobot_drum/custom_task_interfaces/custom_task_interface.py
datarobot_drum/custom_task_interfaces/estimator_interfaces.py
datarobot_drum/custom_task_interfaces/transform_interface.py
datarobot_drum/custom_task_interfaces/user_secrets.py
datarobot_drum/drum/__init__.py
datarobot_drum/drum/args_parser.py
datarobot_drum/drum/common.py
datarobot_drum/drum/data_marshalling.py
datarobot_drum/drum/description.py
datarobot_drum/drum/drum.py
datarobot_drum/drum/entry_point.py
datarobot_drum/drum/enum.py
datarobot_drum/drum/exceptions.py
datarobot_drum/drum/main.py
datarobot_drum/drum/model_metadata.py
datarobot_drum/drum/perf_testing.py
datarobot_drum/drum/push.py
datarobot_drum/drum/resource_monitor.py
datarobot_drum/drum/runtime.py
datarobot_drum/drum/server.py
datarobot_drum/drum/templates_generator.py
datarobot_drum/drum/typeschema_validation.py
datarobot_drum/drum/adapters/__init__.py
datarobot_drum/drum/adapters/cli/__init__.py
datarobot_drum/drum/adapters/cli/drum_fit_adapter.py
datarobot_drum/drum/adapters/cli/drum_score_adapter.py
datarobot_drum/drum/adapters/cli/shared/__init__.py
datarobot_drum/drum/adapters/cli/shared/drum_class_label_adapter.py
datarobot_drum/drum/adapters/cli/shared/drum_input_file_adapter.py
datarobot_drum/drum/adapters/model_adapters/__init__.py
datarobot_drum/drum/adapters/model_adapters/abstract_model_adapter.py
datarobot_drum/drum/adapters/model_adapters/fit.R
datarobot_drum/drum/adapters/model_adapters/python_model_adapter.py
datarobot_drum/drum/adapters/model_adapters/r_model_adapter.py
datarobot_drum/drum/artifact_predictors/__init__.py
datarobot_drum/drum/artifact_predictors/artifact_predictor.py
datarobot_drum/drum/artifact_predictors/keras_predictor.py
datarobot_drum/drum/artifact_predictors/onnx_predictor.py
datarobot_drum/drum/artifact_predictors/sklearn_predictor.py
datarobot_drum/drum/artifact_predictors/torch_predictor.py
datarobot_drum-1.17.11.dist-info/METADATA
datarobot_drum-1.17.11.dist-info/WHEEL
datarobot_drum-1.17.11.dist-info/entry_points.txt
datarobot_drum-1.17.11.dist-info/top_level.txt
datarobot_drum-1.17.11.dist-info/RECORD
