Metadata-Version: 2.4
Name: datarobot-drum
Version: 1.17.11
Summary: DRUM - develop, test and deploy custom models
Home-page: http://datarobot.com
Author: DataRobot
Author-email: support@datarobot.com
License: Apache License, Version 2.0
Project-URL: Source, https://github.com/datarobot/datarobot-user-models
Project-URL: Changelog, https://github.com/datarobot/datarobot-user-models/blob/master/custom_model_runner/CHANGELOG.md
Classifier: Programming Language :: Python :: 3
Classifier: Programming Language :: Python :: 3.8
Classifier: Programming Language :: Python :: 3.9
Classifier: Programming Language :: Python :: 3.10
Classifier: Programming Language :: Python :: 3.11
Classifier: Programming Language :: Python :: 3.12
Classifier: License :: Other/Proprietary License
Classifier: Operating System :: MacOS
Classifier: Operating System :: POSIX
Classifier: Operating System :: Unix
Requires-Python: >=3.8,<3.13
Requires-Dist: argcomplete
Requires-Dist: trafaret>=2.0.0
Requires-Dist: docker>=4.2.2
Requires-Dist: flask
Requires-Dist: jinja2>=3.0.0
Requires-Dist: memory_profiler<1.0.0
Requires-Dist: numpy
Requires-Dist: pandas>=1.5.0
Requires-Dist: progress
Requires-Dist: requests
Requires-Dist: scipy>=1.1
Requires-Dist: strictyaml==1.4.2
Requires-Dist: PyYAML
Requires-Dist: texttable
Requires-Dist: py4j~=0.10.9.0
Requires-Dist: Pillow
Requires-Dist: julia<=0.5.7
Requires-Dist: termcolor
Requires-Dist: packaging
Requires-Dist: markupsafe
Requires-Dist: pydantic
Requires-Dist: gevent
Requires-Dist: gunicorn
Requires-Dist: datarobot-storage
Requires-Dist: datarobot-mlops>=11.1.0a3
Requires-Dist: datarobot<4,>=3.1.0
Requires-Dist: opentelemetry-api
Requires-Dist: opentelemetry-sdk
Requires-Dist: opentelemetry-exporter-otlp-proto-http
Requires-Dist: opentelemetry-instrumentation-aiohttp-client
Requires-Dist: opentelemetry-instrumentation-requests
Provides-Extra: scikit-learn
Requires-Dist: scikit-learn; extra == "scikit-learn"
Requires-Dist: scipy; extra == "scikit-learn"
Requires-Dist: numpy; extra == "scikit-learn"
Provides-Extra: torch
Requires-Dist: torch; extra == "torch"
Requires-Dist: numpy; extra == "torch"
Requires-Dist: scikit-learn; extra == "torch"
Requires-Dist: scipy; extra == "torch"
Provides-Extra: keras
Requires-Dist: scipy; extra == "keras"
Requires-Dist: numpy; extra == "keras"
Requires-Dist: h5py; extra == "keras"
Requires-Dist: tensorflow>=2.2.1; extra == "keras"
Provides-Extra: xgboost
Requires-Dist: scipy; extra == "xgboost"
Requires-Dist: numpy; extra == "xgboost"
Requires-Dist: xgboost; extra == "xgboost"
Provides-Extra: onnx
Requires-Dist: onnxruntime; extra == "onnx"
Provides-Extra: r
Requires-Dist: rpy2==3.5.8; python_version >= "3.6" and extra == "r"
Dynamic: author
Dynamic: author-email
Dynamic: classifier
Dynamic: description
Dynamic: description-content-type
Dynamic: home-page
Dynamic: license
Dynamic: project-url
Dynamic: provides-extra
Dynamic: requires-dist
Dynamic: requires-python
Dynamic: summary
